libtorrent.cpython-310-aarch64-linux-gnu.so
libtorrent-2.0.6.dist-info/RECORD
libtorrent-2.0.6.dist-info/METADATA
libtorrent-2.0.6.dist-info/top_level.txt
libtorrent-2.0.6.dist-info/WHEEL
libtorrent.libs/libstdc++-fd9f4683.so.6.0.28
libtorrent.libs/libgcc_s-4e37474d.so.1
